diet/__init__.py
diet/__main__.py
diet/client_factory.py
diet/configuration.py
diet/diet.py
diet/import_factory.py
diet/dash_import/__init__.py
diet/dash_import/user.py
diet/dash_import/user_org.py
diet-0.1.10.dist-info/METADATA
diet-0.1.10.dist-info/RECORD
diet-0.1.10.dist-info/WHEEL
diet-0.1.10.dist-info/entry_points.txt
diet-0.1.10.dist-info/top_level.txt
