Metadata-Version: 2.1
Name: diet
Version: 0.1.10
Summary: Dash Import Export Tool
Home-page: https://bitbucket.org/sporga/diet
Author: Alexander Burgett
Author-email: alex.burgett@sprga.com.au
License: UNKNOWN
Platform: UNKNOWN
Classifier: Programming Language :: Python :: 2
Classifier: License :: OSI Approved :: MIT License
Classifier: Operating System :: OS Independent
Requires-Dist: dash-api-python-client
Requires-Dist: dash-auth-python-client
Requires-Dist: requests-oauthlib
